choubun/__init__.py
choubun/py.typed
choubun-1.3.1.dist-info/LICENSE
choubun-1.3.1.dist-info/WHEEL
choubun-1.3.1.dist-info/METADATA
choubun-1.3.1.dist-info/RECORD
