Metadata-Version: 2.1
Name: choubun
Version: 1.3.1
Summary: A library for generating HTML and XML from Python using context managers
Home-page: https://gitlab.com/iridescent-aria/choubun
License: MIT
Author: Iridescence
Author-email: iridescent-aria+python@proton.me
Requires-Python: >=3.8,<4.0
Classifier: Development Status :: 4 - Beta
Classifier: Intended Audience :: Developers
Classifier: License :: OSI Approved :: MIT License
Classifier: Operating System :: OS Independent
Classifier: Programming Language :: Python :: 3
Classifier: Programming Language :: Python :: 3.8
Classifier: Programming Language :: Python :: 3.9
Classifier: Programming Language :: Python :: 3.10
Classifier: Programming Language :: Python :: 3.11
Classifier: Topic :: Internet :: WWW/HTTP :: Dynamic Content
Classifier: Topic :: Text Processing :: Markup :: HTML
Classifier: Topic :: Text Processing :: Markup :: XML
Classifier: Typing :: Typed
Requires-Dist: MarkupSafe (>=2.1.1,<3.0.0)
Project-URL: Repository, https://gitlab.com/iridescent-aria/choubun
